veg_workflows/__init__.py
veg_workflows/_version.py
veg_workflows/cdse_browser.py
veg_workflows/collections.py
veg_workflows/colormaps.py
veg_workflows/composite.py
veg_workflows/constants.py
veg_workflows/errors.py
veg_workflows/features.py
veg_workflows/io.py
veg_workflows/products.py
veg_workflows/products_old.py
veg_workflows/tiler.py
veg_workflows/tiles.py
veg_workflows/aws/__init__.py
veg_workflows/aws/lsf_v100.py
veg_workflows/biopar/__init__.py
veg_workflows/biopar/biopar_config.py
veg_workflows/biopar/biopar_config_reader.py
veg_workflows/biopar/biopar_nnw.py
veg_workflows/biopar/processor.py
veg_workflows/cloud/SentinelHubQueryCatalog.ipynb
veg_workflows/cloud/__init__.py
veg_workflows/cloud/azure.py
veg_workflows/cloud/sentinel_hub_query.py
veg_workflows/cloud_mask/__init__.py
veg_workflows/cloud_mask/inference_pipeline.py
veg_workflows/cloud_mask/mask.py
veg_workflows/db/__init__.py
veg_workflows/db/latlon_3deg_grid.db
veg_workflows/db/s2tiles.db
veg_workflows/land_surface/README.md
veg_workflows/land_surface/__init__.py
veg_workflows/land_surface/categories.py
veg_workflows/land_surface/categories_stats.py
veg_workflows/land_surface/composites.py
veg_workflows/paths/__init__.py
veg_workflows/paths/collections.py
veg_workflows/paths/datasets.py
veg_workflows/paths/grids.py
veg_workflows/paths/models.py
veg_workflows/paths/rasters.py
veg_workflows-0.1.9.dev6.dist-info/METADATA
veg_workflows-0.1.9.dev6.dist-info/WHEEL
veg_workflows-0.1.9.dev6.dist-info/RECORD
