Metadata-Version: 2.3
Name: veg-workflows
Version: 0.1.9.dev6
Summary: VEG workflows
Author: VITO RS Vegetation team
Requires-Python: <3.12,>=3.10
Requires-Dist: boto3==1.35.29
Requires-Dist: catboost==1.2.7
Requires-Dist: cloudpickle==3.0.0
Requires-Dist: dask-image==2024.5.3
Requires-Dist: dask==2024.9.1
Requires-Dist: elogs>=0.2.8
Requires-Dist: evotrain==0.0.15.dev0
Requires-Dist: fastparquet==2024.11.0
Requires-Dist: fiona==1.10.1
Requires-Dist: geopandas==1.0.1
Requires-Dist: h5netcdf==1.3.0
Requires-Dist: importlib-resources==6.5.2
Requires-Dist: joblib==1.4.2
Requires-Dist: loguru==0.7.2
Requires-Dist: mepsy==0.0.7
Requires-Dist: numba==0.60.0
Requires-Dist: numpy==1.26.4
Requires-Dist: oauthlib==3.2.2
Requires-Dist: pandas==2.2.3
Requires-Dist: psutil>=7.0
Requires-Dist: pyproj==3.7.0
Requires-Dist: pyspark==3.5.3
Requires-Dist: python-dotenv==1.0.1
Requires-Dist: rasterio>=1.4.0
Requires-Dist: requests-oauthlib==2.0.0
Requires-Dist: rio-cogeo==5.3.4
Requires-Dist: rio-tiler==7.3.0
Requires-Dist: rioxarray>=0.18
Requires-Dist: satio-pc>=0.0.14
Requires-Dist: satio<2.0.0,>=1.2.1
Requires-Dist: scikit-image==0.24.0
Requires-Dist: scikit-learn==1.5.2
Requires-Dist: scipy==1.14.1
Requires-Dist: shapely==2.0.6
Requires-Dist: smart-open[s3]>=7.1.0
Requires-Dist: torch==2.5.1
Requires-Dist: torchvision==0.20.1
Requires-Dist: tqdm==4.66.5
Requires-Dist: watchdog==6.0.0; sys_platform != 'win_ia64'
Requires-Dist: xarray==2025.1.1
Provides-Extra: catalog
Requires-Dist: sentinelhub==3.11.1; extra == 'catalog'
Provides-Extra: jupyter
Requires-Dist: ipykernel==6.29.5; extra == 'jupyter'
Requires-Dist: ipywidgets==8.1.5; extra == 'jupyter'
Requires-Dist: jupyter>=1.1; extra == 'jupyter'
Requires-Dist: jupyterlab==4.2.5; extra == 'jupyter'
Requires-Dist: panel==1.5.5; extra == 'jupyter'
Provides-Extra: plot
Requires-Dist: matplotlib==3.9.2; extra == 'plot'
Requires-Dist: pyproj>=3.7; extra == 'plot'
Requires-Dist: tabulate==0.9.0; extra == 'plot'
